bnl/__init__.py
bnl-0.0.1.dist-info/DESCRIPTION.rst
bnl-0.0.1.dist-info/METADATA
bnl-0.0.1.dist-info/RECORD
bnl-0.0.1.dist-info/WHEEL
bnl-0.0.1.dist-info/metadata.json
bnl-0.0.1.dist-info/top_level.txt
