Metadata-Version: 2.0
Name: bnl
Version: 0.0.1
Summary: Black Earth natural language library
Home-page: https://github.com/BlackEarth/bnl
Author: Sean Harrison
Author-email: sah@blackearth.us
License: LGPL 3.0
Platform: UNKNOWN
Classifier: Development Status :: 3 - Alpha
Classifier: Intended Audience :: Developers
Classifier: License :: OSI Approved :: Mozilla Public License 2.0 (MPL 2.0)
Classifier: Programming Language :: Python :: 3
Requires-Dist: bl
Requires-Dist: spacy
Provides-Extra: dev
Provides-Extra: test
